poweretl/common/__init__.py
poweretl/common/model/__init__.py
poweretl/common/model/config/FileConfigProvider.py
poweretl/common/model/config/__init__.py
poweretl_common-0.0.1a1.dist-info/METADATA
poweretl_common-0.0.1a1.dist-info/WHEEL
poweretl_common-0.0.1a1.dist-info/RECORD
