Metadata-Version: 2.4
Name: poweretl-common
Version: 0.0.1a1
Summary: 
Author: Your Name
Author-email: you@example.com
Requires-Python: >=3.13
Classifier: Programming Language :: Python :: 3
Classifier: Programming Language :: Python :: 3.13
Classifier: Programming Language :: Python :: 3.14
Requires-Dist: dacite (>=1.9.2,<2.0.0)
Requires-Dist: deepmerge (>=2.0,<3.0)
Requires-Dist: json5 (>=0.12.1,<0.13.0)
Requires-Dist: poweretl-defs
Requires-Dist: pyyaml (>=6.0.3,<7.0.0)
